zuspec/__init__.py
zuspec/__main__.py
zuspec/arl_spec_loader.py
zuspec/loader.py
zuspec/my_class.py
zuspec/zuspec.py
zuspec/cmd/__init__.py
zuspec/cmd/cmd_parse_base.py
zuspec/cmd/cmd_registry.py
zuspec/cocotb/__init__.py
zuspec/gen/__init__.py
zuspec/gen/output.py
zuspec/impl/__init__.py
zuspec/impl/ctxt.py
zuspec/impl/generator_dot.py
zuspec/impl/seq_eval_iterator_processor.py
zuspec-0.0.1.6885112054.dist-info/LICENSE
zuspec-0.0.1.6885112054.dist-info/METADATA
zuspec-0.0.1.6885112054.dist-info/WHEEL
zuspec-0.0.1.6885112054.dist-info/entry_points.txt
zuspec-0.0.1.6885112054.dist-info/top_level.txt
zuspec-0.0.1.6885112054.dist-info/RECORD
